slug_model_mixin/__init__.py
slug_model_mixin/apps.py
slug_model_mixin/model_mixins.py
django_slug_model_mixin-0.3.0.dist-info/AUTHORS.rst
django_slug_model_mixin-0.3.0.dist-info/LICENSE.md
django_slug_model_mixin-0.3.0.dist-info/METADATA
django_slug_model_mixin-0.3.0.dist-info/WHEEL
django_slug_model_mixin-0.3.0.dist-info/top_level.txt
django_slug_model_mixin-0.3.0.dist-info/RECORD
