Metadata-Version: 2.1
Name: django-slug-model-mixin
Version: 0.3.0
Summary: Slugify model mixin to manage slugged fields in your project models.
Home-page: https://github.com/frankhood/django-slug-model-mixin
Author: FrankHood Business Solutions srl
Author-email: info@frankhood.it
License: MIT
Keywords: django-slug-model-mixin
Classifier: Development Status :: 3 - Alpha
Classifier: Framework :: Django :: 2.2
Classifier: Framework :: Django :: 3.2
Classifier: Framework :: Django :: 4.2
Classifier: Intended Audience :: Developers
Classifier: License :: OSI Approved :: BSD License
Classifier: Natural Language :: English
Classifier: Programming Language :: Python :: 3.8
Classifier: Programming Language :: Python :: 3.9
Classifier: Programming Language :: Python :: 3.10
License-File: LICENSE.md
License-File: AUTHORS.rst
Requires-Dist: django >=3.2
Requires-Dist: django-uuslug
